[
    {
        "Unique ID": "mpBSMKE4D8.jpg",
        "Name": "mpBSMKE4D8.jpg",
        "Rotation": 0,
        "Scaling": 60,
        "Window": {
            "x": 106,
            "y": 132
        }
    },
    {
        "Unique ID": "Pkroj66an4.jpg",
        "Name": "Pkroj66an4.jpg",
        "Rotation": 0,
        "Scaling": 75,
        "Window": {
            "x": 58,
            "y": 482
        }
    },
    {
        "Unique ID": "fS62c2xUWT.jpg",
        "Name": "fS62c2xUWT.jpg",
        "Rotation": 0,
        "Scaling": 75,
        "Window": {
            "x": 22,
            "y": 494
        }
    },
    {
        "Unique ID": "FvcNHSlZ7N.jpg",
        "Name": "FvcNHSlZ7N.jpg",
        "Rotation": 0,
        "Scaling": 75,
        "Window": {
            "x": 62,
            "y": 200
        }
    },
    {
        "Unique ID": "VMNx4GiCdR.jpg",
        "Name": "VMNx4GiCdR.jpg",
        "Rotation": 0,
        "Scaling": 75,
        "Window": {
            "x": 60,
            "y": 478
        }
    },
    {
        "Unique ID": "iCX17AHy6U.jpg",
        "Name": "iCX17AHy6U.jpg",
        "Rotation": 0,
        "Scaling": 75,
        "Window": {
            "x": 16,
            "y": 344
        }
    },
    {
        "Unique ID": "JFXmfbO2Us.jpg",
        "Name": "JFXmfbO2Us.jpg",
        "Rotation": 0,
        "Scaling": 75,
        "Window": {
            "x": 10,
            "y": 122
        }
    },
    {
        "Unique ID": "pVjzOkvFUI.jpg",
        "Name": "pVjzOkvFUI.jpg",
        "Rotation": 0,
        "Scaling": 40,
        "Window": {
            "x": 156,
            "y": 484
        }
    },
    {
        "Unique ID": "kIq6e2IxYh.jpg",
        "Name": "kIq6e2IxYh.jpg",
        "Rotation": 0,
        "Scaling": 40,
        "Window": {
            "x": 42,
            "y": 312
        }
    }
]